[{"ImportFieldName":"XCoord","Sample":"[128.14381722]","IsExport":false,"Size":null,"SelectedFieldType":{"Key":4,"Value":"String"},"FieldIndex":0,"DesireFieldName":null,"DefaultValue":null,"AliasFieldName":null,"AdditionalValue":null,"AvailableFieldType":[{"Key":0,"Value":"SmallInteger"},{"Key":1,"Value":"Integer"},{"Key":2,"Value":"Single"},{"Key":3,"Value":"Double"},{"Key":4,"Value":"String"},{"Key":5,"Value":"Date"},{"Key":6,"Value":"OID"},{"Key":7,"Value":"Geometry"},{"Key":8,"Value":"Blob"},{"Key":9,"Value":"Raster"},{"Key":10,"Value":"GUID"},{"Key":11,"Value":"GlobalID"},{"Key":12,"Value":"XML"}]},{"ImportFieldName":"YCoord","Sample":"[-9.59192910]","IsExport":false,"Size":null,"SelectedFieldType":{"Key":4,"Value":"String"},"FieldIndex":1,"DesireFieldName":null,"DefaultValue":null,"AliasFieldName":null,"AdditionalValue":null,"AvailableFieldType":[{"Key":0,"Value":"SmallInteger"},{"Key":1,"Value":"Integer"},{"Key":2,"Value":"Single"},{"Key":3,"Value":"Double"},{"Key":4,"Value":"String"},{"Key":5,"Value":"Date"},{"Key":6,"Value":"OID"},{"Key":7,"Value":"Geometry"},{"Key":8,"Value":"Blob"},{"Key":9,"Value":"Raster"},{"Key":10,"Value":"GUID"},{"Key":11,"Value":"GlobalID"},{"Key":12,"Value":"XML"}]},{"ImportFieldName":"LAST_UPDATE","Sample":"[NULL]","IsExport":false,"Size":null,"SelectedFieldType":{"Key":4,"Value":"String"},"FieldIndex":2,"DesireFieldName":null,"DefaultValue":null,"AliasFieldName":null,"AdditionalValue":null,"AvailableFieldType":[{"Key":0,"Value":"SmallInteger"},{"Key":1,"Value":"Integer"},{"Key":2,"Value":"Single"},{"Key":3,"Value":"Double"},{"Key":4,"Value":"String"},{"Key":5,"Value":"Date"},{"Key":6,"Value":"OID"},{"Key":7,"Value":"Geometry"},{"Key":8,"Value":"Blob"},{"Key":9,"Value":"Raster"},{"Key":10,"Value":"GUID"},{"Key":11,"Value":"GlobalID"},{"Key":12,"Value":"XML"}]},{"ImportFieldName":"LAST_UPDATE_BY","Sample":"[Thomas Leong]","IsExport":false,"Size":null,"SelectedFieldType":{"Key":4,"Value":"String"},"FieldIndex":3,"DesireFieldName":null,"DefaultValue":null,"AliasFieldName":null,"AdditionalValue":null,"AvailableFieldType":[{"Key":0,"Value":"SmallInteger"},{"Key":1,"Value":"Integer"},{"Key":2,"Value":"Single"},{"Key":3,"Value":"Double"},{"Key":4,"Value":"String"},{"Key":5,"Value":"Date"},{"Key":6,"Value":"OID"},{"Key":7,"Value":"Geometry"},{"Key":8,"Value":"Blob"},{"Key":9,"Value":"Raster"},{"Key":10,"Value":"GUID"},{"Key":11,"Value":"GlobalID"},{"Key":12,"Value":"XML"}]},{"ImportFieldName":"SURVEY_ID","Sample":"[3]","IsExport":false,"Size":null,"SelectedFieldType":{"Key":4,"Value":"String"},"FieldIndex":4,"DesireFieldName":null,"DefaultValue":null,"AliasFieldName":null,"AdditionalValue":null,"AvailableFieldType":[{"Key":0,"Value":"SmallInteger"},{"Key":1,"Value":"Integer"},{"Key":2,"Value":"Single"},{"Key":3,"Value":"Double"},{"Key":4,"Value":"String"},{"Key":5,"Value":"Date"},{"Key":6,"Value":"OID"},{"Key":7,"Value":"Geometry"},{"Key":8,"Value":"Blob"},{"Key":9,"Value":"Raster"},{"Key":10,"Value":"GUID"},{"Key":11,"Value":"GlobalID"},{"Key":12,"Value":"XML"}]},{"ImportFieldName":"SURVEY_ID_REF","Sample":"[SUN003]","IsExport":false,"Size":null,"SelectedFieldType":{"Key":4,"Value":"String"},"FieldIndex":5,"DesireFieldName":null,"DefaultValue":null,"AliasFieldName":null,"AdditionalValue":null,"AvailableFieldType":[{"Key":0,"Value":"SmallInteger"},{"Key":1,"Value":"Integer"},{"Key":2,"Value":"Single"},{"Key":3,"Value":"Double"},{"Key":4,"Value":"String"},{"Key":5,"Value":"Date"},{"Key":6,"Value":"OID"},{"Key":7,"Value":"Geometry"},{"Key":8,"Value":"Blob"},{"Key":9,"Value":"Raster"},{"Key":10,"Value":"GUID"},{"Key":11,"Value":"GlobalID"},{"Key":12,"Value":"XML"}]},{"ImportFieldName":"REMARKS","Sample":"[Multi-Beam bathymetry is unprocessed and not reliable to use]","IsExport":false,"Size":null,"SelectedFieldType":{"Key":4,"Value":"String"},"FieldIndex":6,"DesireFieldName":null,"DefaultValue":null,"AliasFieldName":null,"AdditionalValue":null,"AvailableFieldType":[{"Key":0,"Value":"SmallInteger"},{"Key":1,"Value":"Integer"},{"Key":2,"Value":"Single"},{"Key":3,"Value":"Double"},{"Key":4,"Value":"String"},{"Key":5,"Value":"Date"},{"Key":6,"Value":"OID"},{"Key":7,"Value":"Geometry"},{"Key":8,"Value":"Blob"},{"Key":9,"Value":"Raster"},{"Key":10,"Value":"GUID"},{"Key":11,"Value":"GlobalID"},{"Key":12,"Value":"XML"}]},{"ImportFieldName":"SURVEY_NAME","Sample":"[Sunrise Troubadour Loxton Shoals - Regional Development Survey]","IsExport":false,"Size":null,"SelectedFieldType":{"Key":4,"Value":"String"},"FieldIndex":7,"DesireFieldName":null,"DefaultValue":null,"AliasFieldName":null,"AdditionalValue":null,"AvailableFieldType":[{"Key":0,"Value":"SmallInteger"},{"Key":1,"Value":"Integer"},{"Key":2,"Value":"Single"},{"Key":3,"Value":"Double"},{"Key":4,"Value":"String"},{"Key":5,"Value":"Date"},{"Key":6,"Value":"OID"},{"Key":7,"Value":"Geometry"},{"Key":8,"Value":"Blob"},{"Key":9,"Value":"Raster"},{"Key":10,"Value":"GUID"},{"Key":11,"Value":"GlobalID"},{"Key":12,"Value":"XML"}]},{"ImportFieldName":"SURVEY_AREA_NAME","Sample":"[Sunrise]","IsExport":false,"Size":null,"SelectedFieldType":{"Key":4,"Value":"String"},"FieldIndex":8,"DesireFieldName":null,"DefaultValue":null,"AliasFieldName":null,"AdditionalValue":null,"AvailableFieldType":[{"Key":0,"Value":"SmallInteger"},{"Key":1,"Value":"Integer"},{"Key":2,"Value":"Single"},{"Key":3,"Value":"Double"},{"Key":4,"Value":"String"},{"Key":5,"Value":"Date"},{"Key":6,"Value":"OID"},{"Key":7,"Value":"Geometry"},{"Key":8,"Value":"Blob"},{"Key":9,"Value":"Raster"},{"Key":10,"Value":"GUID"},{"Key":11,"Value":"GlobalID"},{"Key":12,"Value":"XML"}]},{"ImportFieldName":"SURVEY_TYPE","Sample":"[2]","IsExport":false,"Size":null,"SelectedFieldType":{"Key":4,"Value":"String"},"FieldIndex":9,"DesireFieldName":null,"DefaultValue":null,"AliasFieldName":null,"AdditionalValue":null,"AvailableFieldType":[{"Key":0,"Value":"SmallInteger"},{"Key":1,"Value":"Integer"},{"Key":2,"Value":"Single"},{"Key":3,"Value":"Double"},{"Key":4,"Value":"String"},{"Key":5,"Value":"Date"},{"Key":6,"Value":"OID"},{"Key":7,"Value":"Geometry"},{"Key":8,"Value":"Blob"},{"Key":9,"Value":"Raster"},{"Key":10,"Value":"GUID"},{"Key":11,"Value":"GlobalID"},{"Key":12,"Value":"XML"}]},{"ImportFieldName":"WORK_CATEGORY","Sample":"[ADS]","IsExport":false,"Size":null,"SelectedFieldType":{"Key":4,"Value":"String"},"FieldIndex":10,"DesireFieldName":null,"DefaultValue":null,"AliasFieldName":null,"AdditionalValue":null,"AvailableFieldType":[{"Key":0,"Value":"SmallInteger"},{"Key":1,"Value":"Integer"},{"Key":2,"Value":"Single"},{"Key":3,"Value":"Double"},{"Key":4,"Value":"String"},{"Key":5,"Value":"Date"},{"Key":6,"Value":"OID"},{"Key":7,"Value":"Geometry"},{"Key":8,"Value":"Blob"},{"Key":9,"Value":"Raster"},{"Key":10,"Value":"GUID"},{"Key":11,"Value":"GlobalID"},{"Key":12,"Value":"XML"}]},{"ImportFieldName":"SURVEY_START_DATE","Sample":"[1998-11-07 00:00:00]","IsExport":false,"Size":null,"SelectedFieldType":{"Key":4,"Value":"String"},"FieldIndex":11,"DesireFieldName":null,"DefaultValue":null,"AliasFieldName":null,"AdditionalValue":null,"AvailableFieldType":[{"Key":0,"Value":"SmallInteger"},{"Key":1,"Value":"Integer"},{"Key":2,"Value":"Single"},{"Key":3,"Value":"Double"},{"Key":4,"Value":"String"},{"Key":5,"Value":"Date"},{"Key":6,"Value":"OID"},{"Key":7,"Value":"Geometry"},{"Key":8,"Value":"Blob"},{"Key":9,"Value":"Raster"},{"Key":10,"Value":"GUID"},{"Key":11,"Value":"GlobalID"},{"Key":12,"Value":"XML"}]},{"ImportFieldName":"SURVEY_END_DATE","Sample":"[1998-11-19 00:00:00]","IsExport":false,"Size":null,"SelectedFieldType":{"Key":4,"Value":"String"},"FieldIndex":12,"DesireFieldName":null,"DefaultValue":null,"AliasFieldName":null,"AdditionalValue":null,"AvailableFieldType":[{"Key":0,"Value":"SmallInteger"},{"Key":1,"Value":"Integer"},{"Key":2,"Value":"Single"},{"Key":3,"Value":"Double"},{"Key":4,"Value":"String"},{"Key":5,"Value":"Date"},{"Key":6,"Value":"OID"},{"Key":7,"Value":"Geometry"},{"Key":8,"Value":"Blob"},{"Key":9,"Value":"Raster"},{"Key":10,"Value":"GUID"},{"Key":11,"Value":"GlobalID"},{"Key":12,"Value":"XML"}]},{"ImportFieldName":"REPORT_REF_NO","Sample":"[Svitzer Contract No: 4500017576]","IsExport":false,"Size":null,"SelectedFieldType":{"Key":4,"Value":"String"},"FieldIndex":13,"DesireFieldName":null,"DefaultValue":null,"AliasFieldName":null,"AdditionalValue":null,"AvailableFieldType":[{"Key":0,"Value":"SmallInteger"},{"Key":1,"Value":"Integer"},{"Key":2,"Value":"Single"},{"Key":3,"Value":"Double"},{"Key":4,"Value":"String"},{"Key":5,"Value":"Date"},{"Key":6,"Value":"OID"},{"Key":7,"Value":"Geometry"},{"Key":8,"Value":"Blob"},{"Key":9,"Value":"Raster"},{"Key":10,"Value":"GUID"},{"Key":11,"Value":"GlobalID"},{"Key":12,"Value":"XML"}]},{"ImportFieldName":"REPORT_URL","Sample":"[NULL]","IsExport":false,"Size":null,"SelectedFieldType":{"Key":4,"Value":"String"},"FieldIndex":14,"DesireFieldName":null,"DefaultValue":null,"AliasFieldName":null,"AdditionalValue":null,"AvailableFieldType":[{"Key":0,"Value":"SmallInteger"},{"Key":1,"Value":"Integer"},{"Key":2,"Value":"Single"},{"Key":3,"Value":"Double"},{"Key":4,"Value":"String"},{"Key":5,"Value":"Date"},{"Key":6,"Value":"OID"},{"Key":7,"Value":"Geometry"},{"Key":8,"Value":"Blob"},{"Key":9,"Value":"Raster"},{"Key":10,"Value":"GUID"},{"Key":11,"Value":"GlobalID"},{"Key":12,"Value":"XML"}]},{"ImportFieldName":"CLIENT_NAME","Sample":"[SUN]","IsExport":false,"Size":null,"SelectedFieldType":{"Key":4,"Value":"String"},"FieldIndex":15,"DesireFieldName":null,"DefaultValue":null,"AliasFieldName":null,"AdditionalValue":null,"AvailableFieldType":[{"Key":0,"Value":"SmallInteger"},{"Key":1,"Value":"Integer"},{"Key":2,"Value":"Single"},{"Key":3,"Value":"Double"},{"Key":4,"Value":"String"},{"Key":5,"Value":"Date"},{"Key":6,"Value":"OID"},{"Key":7,"Value":"Geometry"},{"Key":8,"Value":"Blob"},{"Key":9,"Value":"Raster"},{"Key":10,"Value":"GUID"},{"Key":11,"Value":"GlobalID"},{"Key":12,"Value":"XML"}]},{"ImportFieldName":"COUNTRY_NAME","Sample":"[AUS]","IsExport":false,"Size":null,"SelectedFieldType":{"Key":4,"Value":"String"},"FieldIndex":16,"DesireFieldName":null,"DefaultValue":null,"AliasFieldName":null,"AdditionalValue":null,"AvailableFieldType":[{"Key":0,"Value":"SmallInteger"},{"Key":1,"Value":"Integer"},{"Key":2,"Value":"Single"},{"Key":3,"Value":"Double"},{"Key":4,"Value":"String"},{"Key":5,"Value":"Date"},{"Key":6,"Value":"OID"},{"Key":7,"Value":"Geometry"},{"Key":8,"Value":"Blob"},{"Key":9,"Value":"Raster"},{"Key":10,"Value":"GUID"},{"Key":11,"Value":"GlobalID"},{"Key":12,"Value":"XML"}]},{"ImportFieldName":"SYMBOLOGY_CODE","Sample":"[IOGP3600]","IsExport":false,"Size":null,"SelectedFieldType":{"Key":4,"Value":"String"},"FieldIndex":17,"DesireFieldName":null,"DefaultValue":null,"AliasFieldName":null,"AdditionalValue":null,"AvailableFieldType":[{"Key":0,"Value":"SmallInteger"},{"Key":1,"Value":"Integer"},{"Key":2,"Value":"Single"},{"Key":3,"Value":"Double"},{"Key":4,"Value":"String"},{"Key":5,"Value":"Date"},{"Key":6,"Value":"OID"},{"Key":7,"Value":"Geometry"},{"Key":8,"Value":"Blob"},{"Key":9,"Value":"Raster"},{"Key":10,"Value":"GUID"},{"Key":11,"Value":"GlobalID"},{"Key":12,"Value":"XML"}]},{"ImportFieldName":"WORK_DESCRIPTION","Sample":"[MBES]","IsExport":false,"Size":null,"SelectedFieldType":{"Key":4,"Value":"String"},"FieldIndex":18,"DesireFieldName":null,"DefaultValue":null,"AliasFieldName":null,"AdditionalValue":null,"AvailableFieldType":[{"Key":0,"Value":"SmallInteger"},{"Key":1,"Value":"Integer"},{"Key":2,"Value":"Single"},{"Key":3,"Value":"Double"},{"Key":4,"Value":"String"},{"Key":5,"Value":"Date"},{"Key":6,"Value":"OID"},{"Key":7,"Value":"Geometry"},{"Key":8,"Value":"Blob"},{"Key":9,"Value":"Raster"},{"Key":10,"Value":"GUID"},{"Key":11,"Value":"GlobalID"},{"Key":12,"Value":"XML"}]},{"ImportFieldName":"DIMENSION","Sample":"[SSS]","IsExport":false,"Size":null,"SelectedFieldType":{"Key":4,"Value":"String"},"FieldIndex":19,"DesireFieldName":null,"DefaultValue":null,"AliasFieldName":null,"AdditionalValue":null,"AvailableFieldType":[{"Key":0,"Value":"SmallInteger"},{"Key":1,"Value":"Integer"},{"Key":2,"Value":"Single"},{"Key":3,"Value":"Double"},{"Key":4,"Value":"String"},{"Key":5,"Value":"Date"},{"Key":6,"Value":"OID"},{"Key":7,"Value":"Geometry"},{"Key":8,"Value":"Blob"},{"Key":9,"Value":"Raster"},{"Key":10,"Value":"GUID"},{"Key":11,"Value":"GlobalID"},{"Key":12,"Value":"XML"}]}]